jsoner/__init__.py
jsoner/main.py
jsoner_lib-0.5.dist-info/LICENSE
jsoner_lib-0.5.dist-info/METADATA
jsoner_lib-0.5.dist-info/WHEEL
jsoner_lib-0.5.dist-info/top_level.txt
jsoner_lib-0.5.dist-info/RECORD
