Metadata-Version: 2.1
Name: jsoner-lib
Version: 0.5
Home-page: https://github.com/kradt/jsoner
Author: kradt
Author-email: sidorenkoarem950@gmail.com
License: MIT
Keywords: jsoner
Requires-Python: >=3.11
License-File: LICENSE
Requires-Dist: pydantic
